regress_analytics/EDA.py
regress_analytics/__init__.py
regress_analytics/model_performance_analysis.py
regress_analytics/utilities/__init__.py
regress_analytics/utilities/multi_model_prediction.py
regress_analytics/utilities/utils.py
regress_analytics-0.1.3.dist-info/LICENSE
regress_analytics-0.1.3.dist-info/METADATA
regress_analytics-0.1.3.dist-info/WHEEL
regress_analytics-0.1.3.dist-info/top_level.txt
regress_analytics-0.1.3.dist-info/RECORD
