Metadata-Version: 2.1
Name: regress_analytics
Version: 0.1.3
Summary: A tool kit for analyzing regression models
Author-email: Salar Mirzaloo <sal.mirzaloo@gmail.com>
Project-URL: Source Code, https://github.com/mmirz94/regression_analytics_package
Project-URL: Bug Tracker, https://github.com/mmirz94/regression_analytics_package/issues
Project-URL: Sample Notebook, https://github.com/mmirz94/rental_bike_prediction_using_regress_analytics
Classifier: Programming Language :: Python :: 3
Classifier: License :: OSI Approved :: MIT License
Classifier: Operating System :: OS Independent
Requires-Python: >=3.9.0
License-File: LICENSE
Requires-Dist: numpy ==1.23.3
Requires-Dist: pandas ==1.4.2
Requires-Dist: scipy ==1.13.1
Requires-Dist: matplotlib ==3.8.2
Requires-Dist: seaborn ==0.13.2
